{
  "Title": "[HLWN 1-1] NM by Robin",
  "Settings": {
    "Difficulty": 0,
    "Roblox": 1,
    "Speed": 2,
    "AutoSkip": true,
    "UpgradeAll": true
  },
  "Game": {
    "Type": 2,
    "Game": 1,
    "Night": 1
  },
  "Ritual": {
    "Zoom": false,
    "Look": false
  },
  "Units": [
    {
      "X": 389,
      "Y": 433,
      "Window": 1,
      "Upgrade": "N",
      "Key": 49,
      "Target": 0
    },
    {
      "X": 527,
      "Y": 427,
      "Window": 1,
      "Upgrade": "N",
      "Key": 49,
      "Target": 0
    },
    {
      "X": 906,
      "Y": 504,
      "Window": 1,
      "Upgrade": "N",
      "Key": 50,
      "Target": 0
    },
    {
      "X": 797,
      "Y": 514,
      "Window": 1,
      "Upgrade": "N",
      "Key": 50,
      "Target": 0
    },
    {
      "X": 700,
      "Y": 509,
      "Window": 1,
      "Upgrade": "N",
      "Key": 50,
      "Target": 0
    }
  ],
  "Share": {
    "Slot_1": "Paper Pals",
    "Slot_2": "Withered Freddy",
    "Slot_3": "",
    "Slot_4": "",
    "Slot_5": "",
    "Slot_6": "",
    "Notes": "2 Minutes - Both units replaceable.",
	"URL": "https://discord.com/channels/1286211974908215306/1434337222966116489"
  }

}
